{
	"animations": [
		{
			"offsets": [
				0,
				0
			],
			"loop": false,
			"fps": 20,
			"anim": "idle",
			"indices": [],
			"name": "idle"
		},
		{
			"offsets": [
				-2,
				0
			],
			"loop": false,
			"fps": 24,
			"anim": "singRIGHT",
			"indices": [],
			"name": "right"
		},
		{
			"offsets": [
				0,
				0
			],
			"loop": false,
			"fps": 24,
			"anim": "singUP",
			"indices": [],
			"name": "up"
		},
		{
			"offsets": [
				0,
				0
			],
			"loop": false,
			"fps": 24,
			"anim": "singDOWN",
			"indices": [],
			"name": "down"
		},
		{
			"offsets": [
				2,
				0
			],
			"loop": false,
			"fps": 24,
			"anim": "singLEFT",
			"indices": [],
			"name": "left"
		},
		{
			"offsets": [
				0,
				0
			],
			"loop": false,
			"fps": 24,
			"anim": "fist",
			"indices": [],
			"name": "fisting"
		},
		{
			"loop": true,
			"cameraOffset": [
				0,
				0
			],
			"offsets": [
				-2,
				0
			],
			"anim": "walk",
			"fps": 10,
			"name": "walk",
			"indices": []
		}
	],
	"no_antialiasing": true,
	"image": "characters/robicool",
	"position": [
		350,
		570
	],
	"healthicon": "robi",
	"flip_x": false,
	"healthbar_colors": [
		161,
		161,
		161
	],
	"camera_position": [
		-100,
		60
	],
	"sing_duration": 4,
	"scale": 2
}