{
	"animations": [
		{
			"loop": false,
			"cameraOffset": [
				-30,
				0
			],
			"offsets": [
				22,
				0
			],
			"anim": "singLEFT",
			"fps": 24,
			"name": "left",
			"indices": []
		},
		{
			"loop": false,
			"cameraOffset": [
				0,
				30
			],
			"offsets": [
				0,
				0
			],
			"anim": "singDOWN",
			"fps": 24,
			"name": "down",
			"indices": []
		},
		{
			"loop": false,
			"cameraOffset": [
				0,
				-30
			],
			"offsets": [
				0,
				0
			],
			"anim": "singUP",
			"fps": 24,
			"name": "up",
			"indices": []
		},
		{
			"loop": false,
			"cameraOffset": [
				30,
				0
			],
			"offsets": [
				-11,
				0
			],
			"anim": "singRIGHT",
			"fps": 24,
			"name": "right",
			"indices": []
		},
		{
			"offsets": [
				27,
				0
			],
			"cameraOffset": [
				-30,
				0
			],
			"loop": false,
			"fps": 24,
			"anim": "singLEFT-alt",
			"indices": [],
			"name": "otherleft"
		},
		{
			"offsets": [
				0,
				0
			],
			"cameraOffset": [
				0,
				30
			],
			"loop": false,
			"fps": 24,
			"anim": "singDOWN-alt",
			"indices": [],
			"name": "otherdown"
		},
		{
			"offsets": [
				0,
				0
			],
			"cameraOffset": [
				0,
				-30
			],
			"loop": false,
			"fps": 24,
			"anim": "singUP-alt",
			"indices": [],
			"name": "otherup"
		},
		{
			"offsets": [
				-22,
				0
			],
			"cameraOffset": [
				30,
				0
			],
			"loop": false,
			"fps": 24,
			"anim": "singRIGHT-alt",
			"indices": [],
			"name": "otherright"
		},
		{
			"loop": false,
			"cameraOffset": [
				0,
				0
			],
			"offsets": [
				11,
				0
			],
			"anim": "danceU",
			"fps": 20,
			"name": "danceU",
			"indices": []
		},
		{
			"loop": false,
			"cameraOffset": [
				0,
				0
			],
			"offsets": [
				12,
				0
			],
			"anim": "danceL",
			"fps": 20,
			"name": "danceL",
			"indices": []
		},
		{
			"loop": false,
			"cameraOffset": [
				0,
				0
			],
			"offsets": [
				11,
				0
			],
			"anim": "danceR",
			"fps": 20,
			"name": "danceR",
			"indices": []
		},
		{
			"loop": false,
			"cameraOffset": [
				0,
				0
			],
			"offsets": [
				0,
				0
			],
			"anim": "danceRight-alt",
			"fps": 12,
			"name": "danceEright",
			"indices": []
		},
		{
			"loop": false,
			"cameraOffset": [
				0,
				0
			],
			"offsets": [
				0,
				0
			],
			"anim": "danceLeft-alt",
			"fps": 12,
			"name": "danceEleft",
			"indices": []
		},
		{
			"offsets": [
				-22,
				0
			],
			"cameraOffset": [
				0,
				0
			],
			"loop": false,
			"fps": 12,
			"anim": "danceRight-altalt",
			"indices": [],
			"name": "robloxright"
		},
		{
			"offsets": [
				-16,
				0
			],
			"cameraOffset": [
				0,
				0
			],
			"loop": false,
			"fps": 12,
			"anim": "danceLeft-altalt",
			"indices": [],
			"name": "robloxleft"
		},
		{
			"offsets": [
				0,
				0
			],
			"cameraOffset": [
				0,
				0
			],
			"loop": true,
			"fps": 12,
			"anim": "idle-thing",
			"indices": [],
			"name": "thething"
		},
		{
			"loop": false,
			"cameraOffset": [
				-30,
				0
			],
			"offsets": [
				0,
				0
			],
			"anim": "annoyed",
			"fps": 1,
			"name": "unnamused",
			"indices": []
		},
		{
			"loop": false,
			"cameraOffset": [
				0,
				0
			],
			"offsets": [
				0,
				0
			],
			"anim": "shrug",
			"fps": 24,
			"name": "shrug",
			"indices": []
		},
		{
			"loop": false,
			"cameraOffset": [
				0,
				0
			],
			"offsets": [
				0,
				0
			],
			"anim": "middlefinger",
			"fps": 24,
			"name": "middlefinger",
			"indices": []
		},
		{
			"loop": false,
			"cameraOffset": [
				0,
				0
			],
			"offsets": [
				-22,
				27
			],
			"anim": "fire",
			"fps": 24,
			"name": "fire",
			"indices": []
		},
		{
			"loop": false,
			"cameraOffset": [
				0,
				0
			],
			"offsets": [
				0,
				0
			],
			"anim": "danceRight",
			"fps": 12,
			"name": "danceEright",
			"indices": []
		},
		{
			"loop": false,
			"cameraOffset": [
				0,
				0
			],
			"offsets": [
				0,
				0
			],
			"anim": "danceLeft",
			"fps": 12,
			"name": "danceEleft",
			"indices": []
		},
		{
			"offsets": [
				0,
				-11
			],
			"indices": [
				0,
				2,
				2,
				2,
				2,
				2,
				2,
				2,
				2,
				2,
				2,
				2,
				2,
				2,
				2,
				2,
				2,
				2,
				2,
				2,
				2,
				2,
				2,
				2,
				2,
				2,
				2,
				2,
				2,
				2,
				2
			],
			"fps": 12,
			"cameraOffset": [
				0,
				0
			],
			"anim": "surprised",
			"loop": false,
			"name": "suprised"
		}
	],
	"no_antialiasing": true,
	"image": "characters/robi",
	"position": [
		350,
		530
	],
	"healthicon": "robi",
	"flip_x": false,
	"healthbar_colors": [
		90,
		92,
		95
	],
	"camera_position": [
		-130,
		0
	],
	"sing_duration": 6.1,
	"scale": 5.49999999999999
}